FormanceHQ/__init__.py
FormanceHQ/api_client.py
FormanceHQ/configuration.py
FormanceHQ/exceptions.py
FormanceHQ/rest.py
FormanceHQ/schemas.py
FormanceHQ/apis/__init__.py
FormanceHQ/apis/path_to_api.py
FormanceHQ/apis/tag_to_api.py
FormanceHQ/apis/paths/__init__.py
FormanceHQ/apis/paths/api_auth__info.py
FormanceHQ/apis/paths/api_auth_clients.py
FormanceHQ/apis/paths/api_auth_clients_client_id.py
FormanceHQ/apis/paths/api_auth_clients_client_id_scopes_scope_id.py
FormanceHQ/apis/paths/api_auth_clients_client_id_secrets.py
FormanceHQ/apis/paths/api_auth_clients_client_id_secrets_secret_id.py
FormanceHQ/apis/paths/api_auth_scopes.py
FormanceHQ/apis/paths/api_auth_scopes_scope_id.py
FormanceHQ/apis/paths/api_auth_scopes_scope_id_transient_transient_scope_id.py
FormanceHQ/apis/paths/api_auth_users.py
FormanceHQ/apis/paths/api_auth_users_user_id.py
FormanceHQ/apis/paths/api_ledger__info.py
FormanceHQ/apis/paths/api_ledger_ledger__info.py
FormanceHQ/apis/paths/api_ledger_ledger_accounts.py
FormanceHQ/apis/paths/api_ledger_ledger_accounts_address.py
FormanceHQ/apis/paths/api_ledger_ledger_accounts_address_metadata.py
FormanceHQ/apis/paths/api_ledger_ledger_aggregate_balances.py
FormanceHQ/apis/paths/api_ledger_ledger_balances.py
FormanceHQ/apis/paths/api_ledger_ledger_logs.py
FormanceHQ/apis/paths/api_ledger_ledger_mapping.py
FormanceHQ/apis/paths/api_ledger_ledger_script.py
FormanceHQ/apis/paths/api_ledger_ledger_stats.py
FormanceHQ/apis/paths/api_ledger_ledger_transactions.py
FormanceHQ/apis/paths/api_ledger_ledger_transactions_batch.py
FormanceHQ/apis/paths/api_ledger_ledger_transactions_txid.py
FormanceHQ/apis/paths/api_ledger_ledger_transactions_txid_metadata.py
FormanceHQ/apis/paths/api_ledger_ledger_transactions_txid_revert.py
FormanceHQ/apis/paths/api_orchestration__info.py
FormanceHQ/apis/paths/api_orchestration_instances.py
FormanceHQ/apis/paths/api_orchestration_instances_instance_id.py
FormanceHQ/apis/paths/api_orchestration_instances_instance_id_abort.py
FormanceHQ-1.0.20230301.dist-info/METADATA
FormanceHQ-1.0.20230301.dist-info/WHEEL
FormanceHQ-1.0.20230301.dist-info/top_level.txt
FormanceHQ-1.0.20230301.dist-info/RECORD
